{
  "db_name": "PostgreSQL",
  "query": "\n            INSERT INTO dependence_chain(\n                dependence_chain_id,\n                status,\n                last_updated_at,\n                dependency_count\n            )\n            SELECT dcid, 'updated' AS status, ts as last_updated_at, dependency_count\n            FROM unnest($1::bytea[], $2::timestamp[], $3::bigint[]) AS t(dcid, ts, dependency_count)\n            ON CONFLICT (dependence_chain_id) DO UPDATE\n            SET status = 'updated',\n                last_updated_at = GREATEST(\n                    dependence_chain.last_updated_at,\n                    EXCLUDED.last_updated_at\n                )\n            ",
  "describe": {
    "columns": [],
    "parameters": {
      "Left": [
        "ByteaArray",
        "TimestampArray",
        "Int8Array"
      ]
    },
    "nullable": []
  },
  "hash": "d1e5c42539bb901184fe1f4690e62c26850ba790fe0c8d6bdba3adfa18dce89b"
}
