{
  "address": "pS2gMMq6PNZKpjxiANeoN5XxJgwaFsUR6xaJkpUHcDg",
  "metadata": {
    "name": "confidential_token",
    "version": "0.1.0",
    "spec": "0.1.0",
    "description": "Solana PoC confidential token using the Zama host program"
  },
  "docs": [
    "Anchor entrypoint module for the confidential token PoC."
  ],
  "instructions": [
    {
      "name": "confidential_burn",
      "docs": [
        "Burns an encrypted amount by rotating the account balance and encrypted total supply."
      ],
      "discriminator": [
        4,
        132,
        56,
        237,
        159,
        77,
        135,
        180
      ],
      "accounts": [
        {
          "name": "owner",
          "docs": [
            "Token owner and burn authority."
          ],
          "writable": true,
          "signer": true
        },
        {
          "name": "mint",
          "docs": [
            "Confidential mint whose encrypted total supply is decreased."
          ],
          "writable": true
        },
        {
          "name": "token_account",
          "docs": [
            "Token account whose balance is decreased."
          ],
          "writable": true
        },
        {
          "name": "compute_signer",
          "pda": {
            "seeds": [
              {
                "kind": "const",
                "value": [
                  102,
                  104,
                  101,
                  45,
                  99,
                  111,
                  109,
                  112,
                  117,
                  116,
                  101
                ]
              },
              {
                "kind": "account",
                "path": "mint"
              }
            ]
          }
        },
        {
          "name": "total_supply_authority",
          "pda": {
            "seeds": [
              {
                "kind": "const",
                "value": [
                  116,
                  111,
                  116,
                  97,
                  108,
                  45,
                  115,
                  117,
                  112,
                  112,
                  108,
                  121
                ]
              },
              {
                "kind": "account",
                "path": "mint"
              }
            ]
          }
        },
        {
          "name": "balance_value",
          "docs": [
            "Stable balance lineage; read for the current handle and superseded by this eval."
          ],
          "writable": true
        },
        {
          "name": "total_supply_value",
          "docs": [
            "Stable total-supply lineage; read for the current handle and superseded by this eval."
          ],
          "writable": true
        },
        {
          "name": "burned_amount_value",
          "docs": [
            "account's first burn, superseded in place thereafter to each burn's own",
            "delta. Each burn makes its own delta handle publicly decryptable at burn",
            "(ERC-7984 `unwrap` parity), so every burn stays permanently redeemable",
            "even after a later burn supersedes this lineage (DD-036 / Vector 2 closed)."
          ],
          "writable": true
        },
        {
          "name": "zama_event_authority"
        },
        {
          "name": "zama_program",
          "docs": [
            "ZamaHost program used for FHE operations."
          ],
          "address": "6AtbvED1rfX68aCT1tYgU1aeu4kFksPDxZG9gtB1Fgtu"
        },
        {
          "name": "host_config",
          "docs": [
            "ZamaHost config used for handle derivation."
          ]
        },
        {
          "name": "system_program",
          "docs": [
            "System program used for ACL account creation."
          ],
          "address": "11111111111111111111111111111111"
        },
        {
          "name": "hcu_block_meter",
          "docs": [
            "canonical `[\"hcu-block-meter\", compute_signer]` PDA. Supplied by an untrusted mint under a",
            "metering-band cap; omitted when the mint is trusted or the cap is unrestricted."
          ],
          "writable": true,
          "optional": true
        },
        {
          "name": "hcu_trusted_app_record",
          "docs": [
            "canonical `[\"hcu-trusted\", compute_signer]` PDA. Present + valid bypasses the cap; absent",
            "means the mint is metered."
          ],
          "optional": true
        },
        {
          "name": "event_authority"
        },
        {
          "name": "program"
        }
      ],
      "args": [
        {
          "name": "amount_attestation",
          "type": {
            "defined": {
              "name": "CoprocessorInputAttestation"
            }
          }
        }
      ]
    },
    {
      "name": "confidential_transfer",
      "docs": [
        "Transfers an encrypted amount by rotating the sender and recipient balance handles."
      ],
      "discriminator": [
        97,
        79,
        128,
        58,
        134,
        222,
        73,
        143
      ],
      "accounts": [
        {
          "name": "owner",
          "docs": [
            "Sender and transfer authority."
          ],
          "signer": true
        },
        {
          "name": "payer",
          "docs": [
            "Pays rent for the transferred-amount lineage on its first bind."
          ],
          "writable": true,
          "signer": true
        },
        {
          "name": "mint",
          "docs": [
            "Confidential mint."
          ]
        },
        {
          "name": "from_account",
          "docs": [
            "Sender token account."
          ],
          "writable": true
        },
        {
          "name": "to_account",
          "writable": true
        },
        {
          "name": "compute_signer",
          "pda": {
            "seeds": [
              {
                "kind": "const",
                "value": [
                  102,
                  104,
                  101,
                  45,
                  99,
                  111,
                  109,
                  112,
                  117,
                  116,
                  101
                ]
              },
              {
                "kind": "account",
                "path": "mint"
              }
            ]
          }
        },
        {
          "name": "from_balance_value",
          "docs": [
            "Sender's stable balance `EncryptedValue` lineage; read for the current",
            "handle and superseded in place by this eval's CPI."
          ],
          "writable": true
        },
        {
          "name": "to_balance_value",
          "docs": [
            "Recipient's stable balance `EncryptedValue` lineage."
          ],
          "writable": true
        },
        {
          "name": "transferred_amount_value",
          "docs": [
            "the sender's first transfer, superseded thereafter."
          ],
          "writable": true
        },
        {
          "name": "zama_event_authority"
        },
        {
          "name": "zama_program",
          "docs": [
            "ZamaHost program used for FHE operations."
          ],
          "address": "6AtbvED1rfX68aCT1tYgU1aeu4kFksPDxZG9gtB1Fgtu"
        },
        {
          "name": "host_config",
          "docs": [
            "ZamaHost config used for handle derivation."
          ]
        },
        {
          "name": "system_program",
          "docs": [
            "System program used for ACL account creation."
          ],
          "address": "11111111111111111111111111111111"
        },
        {
          "name": "hcu_block_meter",
          "docs": [
            "canonical `[\"hcu-block-meter\", compute_signer]` PDA. The per-mint HCU block meter — supplied",
            "by an untrusted mint under a metering-band cap, omitted otherwise."
          ],
          "writable": true,
          "optional": true
        },
        {
          "name": "hcu_trusted_app_record",
          "docs": [
            "trust witness — present + valid bypasses the cap; absent means untrusted (metered)."
          ],
          "optional": true
        },
        {
          "name": "event_authority"
        },
        {
          "name": "program"
        }
      ],
      "args": [
        {
          "name": "amount_attestation",
          "type": {
            "defined": {
              "name": "CoprocessorInputAttestation"
            }
          }
        }
      ]
    },
    {
      "name": "confidential_transfer_from_value",
      "docs": [
        "Transfers an encrypted amount taken from an existing on-chain `EncryptedValue` (a computed or",
        "received handle) instead of a freshly attested client-side encryption — the path that lets a",
        "contract be the sender of a computed amount (fhevm-internal#1680). The signing owner must be",
        "in the amount value's subject set (the token spend gate); the amount is spent read-only."
      ],
      "discriminator": [
        107,
        168,
        52,
        232,
        133,
        153,
        185,
        191
      ],
      "accounts": [
        {
          "name": "owner",
          "docs": [
            "Sender and transfer authority. Must be in `amount_value`'s subject set (the spend gate)."
          ],
          "signer": true
        },
        {
          "name": "payer",
          "docs": [
            "Pays rent for the transferred-amount lineage on its first bind."
          ],
          "writable": true,
          "signer": true
        },
        {
          "name": "mint",
          "docs": [
            "Confidential mint."
          ]
        },
        {
          "name": "from_account",
          "docs": [
            "Sender token account."
          ],
          "writable": true
        },
        {
          "name": "to_account",
          "writable": true
        },
        {
          "name": "compute_signer",
          "pda": {
            "seeds": [
              {
                "kind": "const",
                "value": [
                  102,
                  104,
                  101,
                  45,
                  99,
                  111,
                  109,
                  112,
                  117,
                  116,
                  101
                ]
              },
              {
                "kind": "account",
                "path": "mint"
              }
            ]
          }
        },
        {
          "name": "from_balance_value",
          "docs": [
            "Sender's stable balance `EncryptedValue` lineage; read for the current",
            "handle and superseded in place by this eval's CPI."
          ],
          "writable": true
        },
        {
          "name": "to_balance_value",
          "docs": [
            "Recipient's stable balance `EncryptedValue` lineage."
          ],
          "writable": true
        },
        {
          "name": "transferred_amount_value",
          "docs": [
            "the sender's first transfer, superseded thereafter."
          ],
          "writable": true
        },
        {
          "name": "amount_value",
          "docs": [
            "The existing encrypted amount to spend: a computed or received `euint64` handle. Read-only",
            "durable operand — never superseded, never consumed. Its address is the canonical PDA of its",
            "own `(acl_domain_key, app_account, encrypted_value_label)` fields, so a lineage from any app",
            "may be passed here once its owner has granted the mint's compute subject via `allow_subjects`."
          ]
        },
        {
          "name": "zama_event_authority"
        },
        {
          "name": "zama_program",
          "docs": [
            "ZamaHost program used for FHE operations."
          ],
          "address": "6AtbvED1rfX68aCT1tYgU1aeu4kFksPDxZG9gtB1Fgtu"
        },
        {
          "name": "host_config",
          "docs": [
            "ZamaHost config used for handle derivation."
          ]
        },
        {
          "name": "system_program",
          "docs": [
            "System program used for ACL account creation."
          ],
          "address": "11111111111111111111111111111111"
        },
        {
          "name": "hcu_block_meter",
          "docs": [
            "canonical `[\"hcu-block-meter\", compute_signer]` PDA. The per-mint HCU block meter — supplied",
            "by an untrusted mint under a metering-band cap, omitted otherwise."
          ],
          "writable": true,
          "optional": true
        },
        {
          "name": "hcu_trusted_app_record",
          "docs": [
            "trust witness — present + valid bypasses the cap; absent means untrusted (metered)."
          ],
          "optional": true
        },
        {
          "name": "event_authority"
        },
        {
          "name": "program"
        }
      ],
      "args": []
    },
    {
      "name": "disclose_secp",
      "docs": [
        "Consumes a KMS public-decrypt certificate through the stateless host verifier and emits a",
        "token-scoped disclosed event. See `instructions::disclose_secp` for the act-once semantics",
        "(idempotent by design — no on-chain replay marker)."
      ],
      "discriminator": [
        151,
        135,
        187,
        69,
        92,
        159,
        136,
        128
      ],
      "accounts": [
        {
          "name": "mint",
          "docs": [
            "Confidential mint whose ACL domain scopes the disclosed lineage and event."
          ]
        },
        {
          "name": "encrypted_value",
          "docs": [
            "The `EncryptedValue` lineage the disclosed handle belongs to.",
            "CPI; this handler additionally binds its `acl_domain_key` to `mint`."
          ]
        },
        {
          "name": "host_config",
          "docs": [
            "Host config carrying the current KMS context id and gateway EIP-712 domain."
          ],
          "pda": {
            "seeds": [
              {
                "kind": "const",
                "value": [
                  104,
                  111,
                  115,
                  116,
                  45,
                  99,
                  111,
                  110,
                  102,
                  105,
                  103
                ]
              }
            ],
            "program": {
              "kind": "const",
              "value": [
                76,
                211,
                2,
                45,
                255,
                80,
                74,
                103,
                92,
                175,
                45,
                155,
                79,
                64,
                20,
                208,
                179,
                220,
                62,
                161,
                127,
                251,
                151,
                186,
                53,
                92,
                236,
                90,
                147,
                58,
                48,
                238
              ]
            }
          }
        },
        {
          "name": "kms_context",
          "docs": [
            "KMS context PDA for the id the certificate commits to (any live context; validated by the",
            "verifier CPI)."
          ]
        },
        {
          "name": "zama_program",
          "docs": [
            "ZamaHost program used for the stateless verifier CPI."
          ],
          "address": "6AtbvED1rfX68aCT1tYgU1aeu4kFksPDxZG9gtB1Fgtu"
        },
        {
          "name": "event_authority"
        },
        {
          "name": "program"
        }
      ],
      "args": [
        {
          "name": "handle",
          "type": {
            "array": [
              "u8",
              32
            ]
          }
        },
        {
          "name": "cleartext",
          "type": {
            "array": [
              "u8",
              32
            ]
          }
        },
        {
          "name": "signatures",
          "type": {
            "vec": {
              "array": [
                "u8",
                65
              ]
            }
          }
        },
        {
          "name": "extra_data",
          "type": "bytes"
        },
        {
          "name": "proof",
          "type": {
            "defined": {
              "name": "MmrInclusionProof"
            }
          }
        }
      ]
    },
    {
      "name": "initialize_mint",
      "docs": [
        "Initializes a confidential mint and records its host ACL domain."
      ],
      "discriminator": [
        209,
        42,
        195,
        4,
        129,
        85,
        209,
        44
      ],
      "accounts": [
        {
          "name": "authority",
          "docs": [
            "Mint authority and rent payer."
          ],
          "writable": true,
          "signer": true
        },
        {
          "name": "mint",
          "docs": [
            "Confidential mint account created by this instruction."
          ],
          "writable": true,
          "signer": true
        },
        {
          "name": "underlying_mint",
          "docs": [
            "Underlying SPL mint wrapped by this confidential mint."
          ]
        },
        {
          "name": "compute_signer",
          "pda": {
            "seeds": [
              {
                "kind": "const",
                "value": [
                  102,
                  104,
                  101,
                  45,
                  99,
                  111,
                  109,
                  112,
                  117,
                  116,
                  101
                ]
              },
              {
                "kind": "account",
                "path": "mint"
              }
            ]
          }
        },
        {
          "name": "total_supply_authority",
          "pda": {
            "seeds": [
              {
                "kind": "const",
                "value": [
                  116,
                  111,
                  116,
                  97,
                  108,
                  45,
                  115,
                  117,
                  112,
                  112,
                  108,
                  121
                ]
              },
              {
                "kind": "account",
                "path": "mint"
              }
            ]
          }
        },
        {
          "name": "total_supply_encrypted_value",
          "writable": true
        },
        {
          "name": "zama_event_authority"
        },
        {
          "name": "zama_program",
          "docs": [
            "ZamaHost program used to create the initial total-supply handle."
          ],
          "address": "6AtbvED1rfX68aCT1tYgU1aeu4kFksPDxZG9gtB1Fgtu"
        },
        {
          "name": "host_config",
          "docs": [
            "ZamaHost config used for handle derivation."
          ]
        },
        {
          "name": "system_program",
          "docs": [
            "System program used for account creation."
          ],
          "address": "11111111111111111111111111111111"
        },
        {
          "name": "hcu_block_meter",
          "docs": [
            "canonical `[\"hcu-block-meter\", compute_signer]` PDA. Supplied by an untrusted mint under a",
            "metering-band cap; omitted when the mint is trusted or the cap is unrestricted."
          ],
          "writable": true,
          "optional": true
        },
        {
          "name": "hcu_trusted_app_record",
          "docs": [
            "canonical `[\"hcu-trusted\", compute_signer]` PDA. Present + valid bypasses the cap; absent",
            "means the mint is metered."
          ],
          "optional": true
        },
        {
          "name": "event_authority"
        },
        {
          "name": "program"
        }
      ],
      "args": []
    },
    {
      "name": "initialize_token_account",
      "docs": [
        "Initializes a token account and creates its initial confidential balance handle."
      ],
      "discriminator": [
        150,
        85,
        44,
        28,
        149,
        14,
        210,
        26
      ],
      "accounts": [
        {
          "name": "owner",
          "docs": [
            "Account owner and rent payer."
          ],
          "writable": true,
          "signer": true
        },
        {
          "name": "mint",
          "docs": [
            "Confidential mint this account belongs to."
          ]
        },
        {
          "name": "compute_signer",
          "pda": {
            "seeds": [
              {
                "kind": "const",
                "value": [
                  102,
                  104,
                  101,
                  45,
                  99,
                  111,
                  109,
                  112,
                  117,
                  116,
                  101
                ]
              },
              {
                "kind": "account",
                "path": "mint"
              }
            ]
          }
        },
        {
          "name": "token_account",
          "writable": true,
          "pda": {
            "seeds": [
              {
                "kind": "const",
                "value": [
                  116,
                  111,
                  107,
                  101,
                  110,
                  45,
                  97,
                  99,
                  99,
                  111,
                  117,
                  110,
                  116
                ]
              },
              {
                "kind": "account",
                "path": "mint"
              },
              {
                "kind": "account",
                "path": "owner"
              }
            ]
          }
        },
        {
          "name": "balance_encrypted_value",
          "writable": true
        },
        {
          "name": "zama_event_authority"
        },
        {
          "name": "zama_program",
          "docs": [
            "ZamaHost program used to create the initial balance handle."
          ],
          "address": "6AtbvED1rfX68aCT1tYgU1aeu4kFksPDxZG9gtB1Fgtu"
        },
        {
          "name": "host_config",
          "docs": [
            "ZamaHost config used for handle derivation."
          ]
        },
        {
          "name": "system_program",
          "docs": [
            "System program used for account creation."
          ],
          "address": "11111111111111111111111111111111"
        },
        {
          "name": "hcu_block_meter",
          "docs": [
            "canonical `[\"hcu-block-meter\", compute_signer]` PDA. Supplied by an untrusted mint under a",
            "metering-band cap; omitted when the mint is trusted or the cap is unrestricted."
          ],
          "writable": true,
          "optional": true
        },
        {
          "name": "hcu_trusted_app_record",
          "docs": [
            "canonical `[\"hcu-trusted\", compute_signer]` PDA. Present + valid bypasses the cap; absent",
            "means the mint is metered."
          ],
          "optional": true
        },
        {
          "name": "event_authority"
        },
        {
          "name": "program"
        }
      ],
      "args": [
        {
          "name": "initial_balance",
          "type": "u64"
        }
      ]
    },
    {
      "name": "redeem_burned_amount",
      "docs": [
        "Redeems a KMS-certified burned amount from the SPL vault through the stateless host verifier.",
        "Verifies the KMS `PublicDecryptVerification` certificate against the context the cert names",
        "(any live, non-destroyed context, EVM-parity rotation grace) plus an exact-handle MMR",
        "public-decrypt proof, then pays out `cleartext_amount` and writes the",
        "permanent per-handle `BurnRedemption` marker. See `instructions::redeem_burned_amount`."
      ],
      "discriminator": [
        75,
        99,
        73,
        176,
        121,
        166,
        244,
        3
      ],
      "accounts": [
        {
          "name": "owner",
          "docs": [
            "Token owner, redemption recipient, and payer for the replay marker."
          ],
          "writable": true,
          "signer": true
        },
        {
          "name": "mint",
          "docs": [
            "Confidential mint whose vault backs the redeemed burned amount."
          ]
        },
        {
          "name": "token_account",
          "docs": [
            "Confidential token account that produced the burned amount."
          ]
        },
        {
          "name": "underlying_mint",
          "docs": [
            "Underlying SPL mint."
          ]
        },
        {
          "name": "vault_usdc",
          "docs": [
            "Program vault USDC token account."
          ],
          "writable": true
        },
        {
          "name": "destination_usdc",
          "docs": [
            "Signer's destination USDC token account (any SPL account of the right mint owned by the",
            "signer, not necessarily the ATA)."
          ],
          "writable": true
        },
        {
          "name": "vault_authority",
          "pda": {
            "seeds": [
              {
                "kind": "const",
                "value": [
                  118,
                  97,
                  117,
                  108,
                  116,
                  45,
                  97,
                  117,
                  116,
                  104,
                  111,
                  114,
                  105,
                  116,
                  121
                ]
              },
              {
                "kind": "account",
                "path": "mint"
              }
            ]
          }
        },
        {
          "name": "burned_amount_value",
          "docs": [
            "Burned amount `EncryptedValue` lineage whose handle is redeemed. Bound to the mint/token",
            "account/owner by `assert_burned_amount_lineage`; its canonical PDA, layout, host ownership,",
            "and the exact-handle MMR inclusion proof are validated by the `verify_public_decrypt` CPI."
          ]
        },
        {
          "name": "redemption_record",
          "docs": [
            "Replay marker for this burned handle: write-once, never closed, the sole durable \"paid out\"",
            "bit for `(mint, burned_handle)`."
          ],
          "writable": true,
          "pda": {
            "seeds": [
              {
                "kind": "const",
                "value": [
                  98,
                  117,
                  114,
                  110,
                  45,
                  114,
                  101,
                  100,
                  101,
                  109,
                  112,
                  116,
                  105,
                  111,
                  110
                ]
              },
              {
                "kind": "account",
                "path": "mint"
              },
              {
                "kind": "arg",
                "path": "burned_handle"
              }
            ]
          }
        },
        {
          "name": "host_config",
          "docs": [
            "Host config carrying the current KMS context id and gateway EIP-712 domain."
          ],
          "pda": {
            "seeds": [
              {
                "kind": "const",
                "value": [
                  104,
                  111,
                  115,
                  116,
                  45,
                  99,
                  111,
                  110,
                  102,
                  105,
                  103
                ]
              }
            ],
            "program": {
              "kind": "const",
              "value": [
                76,
                211,
                2,
                45,
                255,
                80,
                74,
                103,
                92,
                175,
                45,
                155,
                79,
                64,
                20,
                208,
                179,
                220,
                62,
                161,
                127,
                251,
                151,
                186,
                53,
                92,
                236,
                90,
                147,
                58,
                48,
                238
              ]
            }
          }
        },
        {
          "name": "kms_context",
          "docs": [
            "KMS context PDA for the id the certificate commits to (any live context; validated by the",
            "verifier CPI)."
          ]
        },
        {
          "name": "deny_subject_record",
          "docs": [
            "consulted read-only by `assert_redeem_subject_not_denied`. Absent (must be `None`) when the",
            "deny-list is disabled."
          ],
          "optional": true
        },
        {
          "name": "zama_program",
          "docs": [
            "ZamaHost program used for the stateless verifier CPI."
          ],
          "address": "6AtbvED1rfX68aCT1tYgU1aeu4kFksPDxZG9gtB1Fgtu"
        },
        {
          "name": "token_program",
          "docs": [
            "SPL token program."
          ],
          "address": "TokenkegQfeZyiNwAJbNbGKPFXCWuBvf9Ss623VQ5DA"
        },
        {
          "name": "system_program",
          "docs": [
            "System program used for the replay marker."
          ],
          "address": "11111111111111111111111111111111"
        },
        {
          "name": "event_authority"
        },
        {
          "name": "program"
        }
      ],
      "args": [
        {
          "name": "burned_handle",
          "type": {
            "array": [
              "u8",
              32
            ]
          }
        },
        {
          "name": "cleartext_amount",
          "type": "u64"
        },
        {
          "name": "signatures",
          "type": {
            "vec": {
              "array": [
                "u8",
                65
              ]
            }
          }
        },
        {
          "name": "extra_data",
          "type": "bytes"
        },
        {
          "name": "proof",
          "type": {
            "defined": {
              "name": "MmrInclusionProof"
            }
          }
        }
      ]
    },
    {
      "name": "wrap_usdc",
      "docs": [
        "Escrows public USDC and rotates the confidential balance by `amount`."
      ],
      "discriminator": [
        88,
        246,
        99,
        254,
        37,
        183,
        111,
        12
      ],
      "accounts": [
        {
          "name": "owner",
          "docs": [
            "Token owner and transfer authority."
          ],
          "writable": true,
          "signer": true
        },
        {
          "name": "mint",
          "docs": [
            "Confidential mint."
          ],
          "writable": true
        },
        {
          "name": "token_account",
          "docs": [
            "Confidential token account whose balance is increased."
          ],
          "writable": true
        },
        {
          "name": "underlying_mint",
          "docs": [
            "Underlying SPL mint."
          ]
        },
        {
          "name": "user_usdc",
          "docs": [
            "Owner's source USDC token account."
          ],
          "writable": true
        },
        {
          "name": "vault_usdc",
          "docs": [
            "Program vault USDC token account."
          ],
          "writable": true
        },
        {
          "name": "vault_authority",
          "pda": {
            "seeds": [
              {
                "kind": "const",
                "value": [
                  118,
                  97,
                  117,
                  108,
                  116,
                  45,
                  97,
                  117,
                  116,
                  104,
                  111,
                  114,
                  105,
                  116,
                  121
                ]
              },
              {
                "kind": "account",
                "path": "mint"
              }
            ]
          }
        },
        {
          "name": "compute_signer",
          "pda": {
            "seeds": [
              {
                "kind": "const",
                "value": [
                  102,
                  104,
                  101,
                  45,
                  99,
                  111,
                  109,
                  112,
                  117,
                  116,
                  101
                ]
              },
              {
                "kind": "account",
                "path": "mint"
              }
            ]
          }
        },
        {
          "name": "total_supply_authority",
          "pda": {
            "seeds": [
              {
                "kind": "const",
                "value": [
                  116,
                  111,
                  116,
                  97,
                  108,
                  45,
                  115,
                  117,
                  112,
                  112,
                  108,
                  121
                ]
              },
              {
                "kind": "account",
                "path": "mint"
              }
            ]
          }
        },
        {
          "name": "balance_value",
          "docs": [
            "Stable balance lineage; read for the current handle and superseded by this eval."
          ],
          "writable": true
        },
        {
          "name": "total_supply_value",
          "docs": [
            "Stable total-supply lineage; read for the current handle and superseded by this eval."
          ],
          "writable": true
        },
        {
          "name": "zama_event_authority"
        },
        {
          "name": "zama_program",
          "docs": [
            "ZamaHost program used for FHE operations."
          ],
          "address": "6AtbvED1rfX68aCT1tYgU1aeu4kFksPDxZG9gtB1Fgtu"
        },
        {
          "name": "host_config",
          "docs": [
            "ZamaHost config used for handle derivation."
          ]
        },
        {
          "name": "token_program",
          "docs": [
            "SPL token program."
          ],
          "address": "TokenkegQfeZyiNwAJbNbGKPFXCWuBvf9Ss623VQ5DA"
        },
        {
          "name": "system_program",
          "docs": [
            "System program used for ACL account creation."
          ],
          "address": "11111111111111111111111111111111"
        },
        {
          "name": "hcu_block_meter",
          "docs": [
            "canonical `[\"hcu-block-meter\", compute_signer]` PDA. Supplied by an untrusted mint under a",
            "metering-band cap; omitted when the mint is trusted or the cap is unrestricted."
          ],
          "writable": true,
          "optional": true
        },
        {
          "name": "hcu_trusted_app_record",
          "docs": [
            "canonical `[\"hcu-trusted\", compute_signer]` PDA. Present + valid bypasses the cap; absent",
            "means the mint is metered."
          ],
          "optional": true
        },
        {
          "name": "event_authority"
        },
        {
          "name": "program"
        }
      ],
      "args": [
        {
          "name": "amount",
          "type": "u64"
        }
      ]
    }
  ],
  "accounts": [
    {
      "name": "BurnRedemption",
      "discriminator": [
        98,
        115,
        13,
        164,
        230,
        159,
        128,
        195
      ]
    },
    {
      "name": "ConfidentialMint",
      "discriminator": [
        63,
        117,
        199,
        24,
        52,
        30,
        202,
        4
      ]
    },
    {
      "name": "ConfidentialTokenAccount",
      "discriminator": [
        162,
        241,
        85,
        134,
        20,
        132,
        103,
        199
      ]
    }
  ],
  "events": [
    {
      "name": "BalanceHandleUpdatedEvent",
      "discriminator": [
        218,
        115,
        100,
        232,
        176,
        152,
        68,
        72
      ]
    },
    {
      "name": "BurnRedeemedEvent",
      "discriminator": [
        6,
        82,
        161,
        171,
        88,
        140,
        98,
        152
      ]
    },
    {
      "name": "ConfidentialBurnEvent",
      "discriminator": [
        218,
        41,
        125,
        0,
        227,
        226,
        179,
        50
      ]
    },
    {
      "name": "ConfidentialTransferEvent",
      "discriminator": [
        24,
        221,
        223,
        133,
        221,
        78,
        35,
        85
      ]
    },
    {
      "name": "HandleDisclosedEvent",
      "discriminator": [
        134,
        63,
        113,
        175,
        107,
        120,
        122,
        51
      ]
    },
    {
      "name": "RandomAmountCreatedEvent",
      "discriminator": [
        197,
        125,
        32,
        173,
        115,
        70,
        150,
        4
      ]
    },
    {
      "name": "TotalSupplyHandleUpdatedEvent",
      "discriminator": [
        140,
        218,
        185,
        16,
        174,
        158,
        75,
        70
      ]
    }
  ],
  "errors": [
    {
      "code": 6000,
      "name": "OwnerMismatch",
      "msg": "Token owner does not match signer"
    },
    {
      "code": 6001,
      "name": "MintMismatch",
      "msg": "Token account mint does not match"
    },
    {
      "code": 6002,
      "name": "MintAccountMismatch",
      "msg": "Confidential mint account is invalid"
    },
    {
      "code": 6003,
      "name": "InvalidMintConfig",
      "msg": "Confidential mint config is invalid"
    },
    {
      "code": 6004,
      "name": "MintAuthorityMismatch",
      "msg": "Confidential mint authority does not match signer"
    },
    {
      "code": 6005,
      "name": "UnexpectedRemainingAccounts",
      "msg": "instruction has unexpected remaining accounts"
    },
    {
      "code": 6006,
      "name": "TokenAccountMismatch",
      "msg": "Confidential token account is not canonical"
    },
    {
      "code": 6007,
      "name": "AclNonceOverflow",
      "msg": "ACL nonce overflow"
    },
    {
      "code": 6008,
      "name": "NonZeroInitialBalanceUnsupported",
      "msg": "nonzero initial confidential balances are unsupported"
    },
    {
      "code": 6009,
      "name": "UnderlyingMintMismatch",
      "msg": "Underlying mint does not match confidential mint"
    },
    {
      "code": 6010,
      "name": "VaultAuthorityMismatch",
      "msg": "Vault token account authority does not match vault authority PDA"
    },
    {
      "code": 6011,
      "name": "VaultAccountMismatch",
      "msg": "Vault token account is not the canonical mint vault"
    },
    {
      "code": 6012,
      "name": "AclDomainKeyMismatch",
      "msg": "Confidential mint ACL domain key is invalid"
    },
    {
      "code": 6013,
      "name": "ComputeSignerMismatch",
      "msg": "Compute signer does not match confidential mint"
    },
    {
      "code": 6014,
      "name": "CurrentEncryptedValueMismatch",
      "msg": "current encrypted value does not match token account state"
    },
    {
      "code": 6015,
      "name": "AmountHandleTypeMismatch",
      "msg": "transfer amount handle type is invalid"
    },
    {
      "code": 6016,
      "name": "AmountAclMismatch",
      "msg": "transfer amount ACL record is invalid"
    },
    {
      "code": 6017,
      "name": "AttestationUserMismatch",
      "msg": "attested input user does not match owner"
    },
    {
      "code": 6018,
      "name": "AttestationContractMismatch",
      "msg": "attested input contract does not match compute signer"
    },
    {
      "code": 6019,
      "name": "AmountSpendSubjectMismatch",
      "msg": "amount value spender is not in the amount's subject set"
    },
    {
      "code": 6020,
      "name": "TotalSupplyAuthorityMismatch",
      "msg": "total supply authority does not match mint"
    },
    {
      "code": 6021,
      "name": "InvalidKmsCertificate",
      "msg": "KMS public-decrypt certificate is invalid"
    },
    {
      "code": 6022,
      "name": "PublicDecryptProofInvalid",
      "msg": "public-decrypt MMR proof is invalid for this lineage"
    },
    {
      "code": 6023,
      "name": "GatewayVerifierConfigUnset",
      "msg": "gateway verifier config is not set"
    },
    {
      "code": 6024,
      "name": "InvalidKmsContext",
      "msg": "KMS context is not valid for this request"
    },
    {
      "code": 6025,
      "name": "RequestWitnessMismatch",
      "msg": "request witness does not match"
    },
    {
      "code": 6026,
      "name": "RequestWitnessUnavailable",
      "msg": "request witness is expired or already consumed"
    },
    {
      "code": 6027,
      "name": "MaterialCommitmentMismatch",
      "msg": "material commitment witness does not match (retired)"
    },
    {
      "code": 6028,
      "name": "PublicDecryptNotReleased",
      "msg": "handle is not released for public decrypt (retired)"
    },
    {
      "code": 6029,
      "name": "InvalidFheEvalPlan",
      "msg": "FHE eval plan is invalid"
    },
    {
      "code": 6030,
      "name": "DuplicateFheEvalAccount",
      "msg": "FHE eval account list contains a duplicate account"
    },
    {
      "code": 6031,
      "name": "UnexpectedFheEvalAccount",
      "msg": "FHE eval account list contains an unexpected account"
    },
    {
      "code": 6032,
      "name": "MissingFheEvalAccount",
      "msg": "FHE eval plan is missing a required dynamic account"
    },
    {
      "code": 6033,
      "name": "FheEvalAccountNotWritable",
      "msg": "FHE eval dynamic account must be writable"
    },
    {
      "code": 6034,
      "name": "DuplicateFheOutputAuthority",
      "msg": "FHE eval output authority list contains a duplicate authority"
    },
    {
      "code": 6035,
      "name": "UnexpectedFheOutputAuthority",
      "msg": "FHE eval output authority list contains an unexpected authority"
    },
    {
      "code": 6036,
      "name": "MissingFheOutputAuthority",
      "msg": "FHE eval plan is missing a required output authority"
    },
    {
      "code": 6037,
      "name": "VerifierReturnDataInvalid",
      "msg": "public-decrypt verifier return data is invalid"
    },
    {
      "code": 6038,
      "name": "DisclosedHandleMismatch",
      "msg": "disclosed handle does not match the pinned handle"
    },
    {
      "code": 6039,
      "name": "RedemptionSubjectDenied",
      "msg": "redemption subject is denied"
    },
    {
      "code": 6040,
      "name": "RedemptionDenyRecordInvalid",
      "msg": "redemption deny-list record is invalid"
    },
    {
      "code": 6041,
      "name": "CleartextExceedsEuint64",
      "msg": "certified cleartext exceeds euint64 width"
    }
  ],
  "types": [
    {
      "name": "BalanceHandleUpdateReason",
      "docs": [
        "Reason code for [`BalanceHandleUpdatedEvent`]."
      ],
      "type": {
        "kind": "enum",
        "variants": [
          {
            "name": "Initialize"
          },
          {
            "name": "Wrap"
          },
          {
            "name": "TransferDebit"
          },
          {
            "name": "TransferCredit"
          },
          {
            "name": "BurnDebit"
          }
        ]
      }
    },
    {
      "name": "BalanceHandleUpdatedEvent",
      "docs": [
        "App-local balance history event.",
        "",
        "This event is for frontend/app indexers. The generic coprocessor listener",
        "consumes ZamaHost protocol events instead."
      ],
      "type": {
        "kind": "struct",
        "fields": [
          {
            "name": "version",
            "docs": [
              "Event schema version."
            ],
            "type": "u8"
          },
          {
            "name": "mint",
            "docs": [
              "Confidential mint."
            ],
            "type": "pubkey"
          },
          {
            "name": "owner",
            "docs": [
              "Token account owner."
            ],
            "type": "pubkey"
          },
          {
            "name": "token_account",
            "docs": [
              "Confidential token account."
            ],
            "type": "pubkey"
          },
          {
            "name": "old_handle",
            "docs": [
              "Previous balance handle."
            ],
            "type": {
              "array": [
                "u8",
                32
              ]
            }
          },
          {
            "name": "old_encrypted_value",
            "docs": [
              "Previous ZamaHost ACL record."
            ],
            "type": "pubkey"
          },
          {
            "name": "new_handle",
            "docs": [
              "New balance handle."
            ],
            "type": {
              "array": [
                "u8",
                32
              ]
            }
          },
          {
            "name": "new_encrypted_value",
            "docs": [
              "New ZamaHost ACL record."
            ],
            "type": "pubkey"
          },
          {
            "name": "reason",
            "docs": [
              "Reason this balance pointer changed."
            ],
            "type": {
              "defined": {
                "name": "BalanceHandleUpdateReason"
              }
            }
          }
        ]
      }
    },
    {
      "name": "BurnRedeemedEvent",
      "docs": [
        "Emitted when a KMS-certified burned amount is redeemed from the vault.",
        "",
        "After the `BurnRedemptionRequest` witness lifecycle was dissolved (fhevm-internal#1763), redeem is",
        "a single instruction with no request witness, so this event no longer carries a `request` PDA or",
        "`request_hash`."
      ],
      "type": {
        "kind": "struct",
        "fields": [
          {
            "name": "version",
            "docs": [
              "Event schema version."
            ],
            "type": "u8"
          },
          {
            "name": "mint",
            "docs": [
              "Confidential mint."
            ],
            "type": "pubkey"
          },
          {
            "name": "owner",
            "docs": [
              "Token account owner."
            ],
            "type": "pubkey"
          },
          {
            "name": "token_account",
            "docs": [
              "Confidential token account that produced the burned amount."
            ],
            "type": "pubkey"
          },
          {
            "name": "burned_handle",
            "docs": [
              "Burned amount handle proven by KMS."
            ],
            "type": {
              "array": [
                "u8",
                32
              ]
            }
          },
          {
            "name": "burned_encrypted_value",
            "docs": [
              "ACL record for `burned_handle`."
            ],
            "type": "pubkey"
          },
          {
            "name": "destination_usdc",
            "docs": [
              "Underlying token destination account."
            ],
            "type": "pubkey"
          },
          {
            "name": "cleartext_amount",
            "docs": [
              "KMS-certified cleartext amount released from the vault."
            ],
            "type": "u64"
          }
        ]
      }
    },
    {
      "name": "BurnRedemption",
      "docs": [
        "Replay marker for a redeemed burned amount handle."
      ],
      "type": {
        "kind": "struct",
        "fields": [
          {
            "name": "mint",
            "docs": [
              "Confidential mint whose vault paid the redemption."
            ],
            "type": "pubkey"
          },
          {
            "name": "owner",
            "docs": [
              "Token owner that redeemed the burned amount."
            ],
            "type": "pubkey"
          },
          {
            "name": "token_account",
            "docs": [
              "Token account that produced the burned amount."
            ],
            "type": "pubkey"
          },
          {
            "name": "burned_handle",
            "docs": [
              "Burned amount handle proven by KMS."
            ],
            "type": {
              "array": [
                "u8",
                32
              ]
            }
          },
          {
            "name": "burned_encrypted_value",
            "docs": [
              "`EncryptedValue` lineage for `burned_handle`."
            ],
            "type": "pubkey"
          },
          {
            "name": "cleartext_amount",
            "docs": [
              "KMS-certified cleartext amount released from the vault."
            ],
            "type": "u64"
          },
          {
            "name": "bump",
            "docs": [
              "PDA bump for `(mint, burned_handle)`."
            ],
            "type": "u8"
          }
        ]
      }
    },
    {
      "name": "ConfidentialAmountKind",
      "docs": [
        "Token-scoped amount purpose used for amount-handle birth."
      ],
      "type": {
        "kind": "enum",
        "variants": [
          {
            "name": "Transfer"
          },
          {
            "name": "Burn"
          }
        ]
      }
    },
    {
      "name": "ConfidentialBurnEvent",
      "docs": [
        "Emitted when a confidential burn computes the all-or-zero burned amount."
      ],
      "type": {
        "kind": "struct",
        "fields": [
          {
            "name": "version",
            "docs": [
              "Event schema version."
            ],
            "type": "u8"
          },
          {
            "name": "mint",
            "docs": [
              "Confidential mint."
            ],
            "type": "pubkey"
          },
          {
            "name": "owner",
            "docs": [
              "Token account owner."
            ],
            "type": "pubkey"
          },
          {
            "name": "token_account",
            "docs": [
              "Token account whose balance was debited."
            ],
            "type": "pubkey"
          },
          {
            "name": "burned_handle",
            "docs": [
              "Encrypted amount actually burned."
            ],
            "type": {
              "array": [
                "u8",
                32
              ]
            }
          },
          {
            "name": "burned_encrypted_value",
            "docs": [
              "ZamaHost ACL record for `burned_handle`."
            ],
            "type": "pubkey"
          }
        ]
      }
    },
    {
      "name": "ConfidentialMint",
      "docs": [
        "Confidential mint state for the token PoC.",
        "",
        "The total supply's current handle and access lineage live in the",
        "`EncryptedValue` account at `total_supply_encrypted_value`."
      ],
      "type": {
        "kind": "struct",
        "fields": [
          {
            "name": "authority",
            "docs": [
              "Admin/authority that created the mint."
            ],
            "type": "pubkey"
          },
          {
            "name": "acl_domain_key",
            "docs": [
              "ACL domain key, currently equal to the mint pubkey."
            ],
            "type": "pubkey"
          },
          {
            "name": "compute_signer",
            "docs": [
              "Program-controlled compute signer PDA."
            ],
            "type": "pubkey"
          },
          {
            "name": "underlying_mint",
            "docs": [
              "Underlying SPL mint wrapped by this confidential mint."
            ],
            "type": "pubkey"
          },
          {
            "name": "decimals",
            "docs": [
              "Decimal precision inherited from the underlying mint."
            ],
            "type": "u8"
          },
          {
            "name": "total_supply_encrypted_value",
            "docs": [
              "`EncryptedValue` lineage PDA holding the current total-supply handle."
            ],
            "type": "pubkey"
          }
        ]
      }
    },
    {
      "name": "ConfidentialTokenAccount",
      "docs": [
        "Confidential token account state.",
        "",
        "The balance's current handle and access lineage live in the",
        "`EncryptedValue` account at `balance_encrypted_value`, not here — addressing",
        "is stable per token account, so no nonce/sequence bookkeeping is needed."
      ],
      "type": {
        "kind": "struct",
        "fields": [
          {
            "name": "owner",
            "docs": [
              "Token account owner."
            ],
            "type": "pubkey"
          },
          {
            "name": "mint",
            "docs": [
              "Confidential mint this account belongs to."
            ],
            "type": "pubkey"
          },
          {
            "name": "balance_encrypted_value",
            "docs": [
              "`EncryptedValue` lineage PDA holding the current balance handle."
            ],
            "type": "pubkey"
          },
          {
            "name": "bump",
            "docs": [
              "PDA bump for the token account."
            ],
            "type": "u8"
          }
        ]
      }
    },
    {
      "name": "ConfidentialTransferEvent",
      "docs": [
        "Emitted when a confidential transfer computes the all-or-zero moved amount."
      ],
      "type": {
        "kind": "struct",
        "fields": [
          {
            "name": "version",
            "docs": [
              "Event schema version."
            ],
            "type": "u8"
          },
          {
            "name": "mint",
            "docs": [
              "Confidential mint."
            ],
            "type": "pubkey"
          },
          {
            "name": "from_owner",
            "docs": [
              "Sender token account owner."
            ],
            "type": "pubkey"
          },
          {
            "name": "from_token_account",
            "docs": [
              "Sender confidential token account."
            ],
            "type": "pubkey"
          },
          {
            "name": "to_owner",
            "docs": [
              "Recipient token account owner."
            ],
            "type": "pubkey"
          },
          {
            "name": "to_token_account",
            "docs": [
              "Recipient confidential token account."
            ],
            "type": "pubkey"
          },
          {
            "name": "transferred_handle",
            "docs": [
              "Encrypted amount actually transferred."
            ],
            "type": {
              "array": [
                "u8",
                32
              ]
            }
          },
          {
            "name": "transferred_encrypted_value",
            "docs": [
              "ZamaHost ACL record for `transferred_handle`."
            ],
            "type": "pubkey"
          }
        ]
      }
    },
    {
      "name": "CoprocessorInputAttestation",
      "docs": [
        "A coprocessor input attestation carried inline by a [`FheEvalOperand::VerifiedInput`], re-verified",
        "in-frame (no account, no PDA) — the instruction-local analog of EVM `allowTransient(input, contract)`."
      ],
      "type": {
        "kind": "struct",
        "fields": [
          {
            "name": "input_handle",
            "docs": [
              "The verified input handle used as the operand."
            ],
            "type": {
              "array": [
                "u8",
                32
              ]
            }
          },
          {
            "name": "ct_handles",
            "docs": [
              "All ciphertext handles covered by the proof."
            ],
            "type": {
              "vec": {
                "array": [
                  "u8",
                  32
                ]
              }
            }
          },
          {
            "name": "handle_index",
            "docs": [
              "Index of `input_handle` within `ct_handles`."
            ],
            "type": "u8"
          },
          {
            "name": "user_address",
            "docs": [
              "Attested user identity (bytes32)."
            ],
            "type": {
              "array": [
                "u8",
                32
              ]
            }
          },
          {
            "name": "contract_address",
            "docs": [
              "Attested contract identity — the input's ACL domain key (bytes32)."
            ],
            "type": {
              "array": [
                "u8",
                32
              ]
            }
          },
          {
            "name": "contract_chain_id",
            "docs": [
              "Gateway-side contract chain id the attestation binds."
            ],
            "type": "u64"
          },
          {
            "name": "extra_data",
            "docs": [
              "Opaque extra data covered by the attestation."
            ],
            "type": "bytes"
          },
          {
            "name": "signatures",
            "docs": [
              "Coprocessor EIP-712 signatures (65-byte secp256k1)."
            ],
            "type": {
              "vec": {
                "array": [
                  "u8",
                  65
                ]
              }
            }
          }
        ]
      }
    },
    {
      "name": "EncryptedValue",
      "docs": [
        "Canonical ACL + history state for one encrypted-value lineage.",
        "",
        "PDA: `[ENCRYPTED_VALUE_SEED, value_key]` where `value_key =",
        "zama_solana_acl::derive_value_key(acl_domain_key, app_account, encrypted_value_label)`.",
        "The account name must stay exactly `EncryptedValue` — Anchor derives the",
        "discriminator from the type name, and it must match",
        "`zama_solana_acl::encrypted_value_discriminator()`."
      ],
      "type": {
        "kind": "struct",
        "fields": [
          {
            "name": "acl_domain_key",
            "docs": [
              "App-level ACL domain, such as a confidential token mint."
            ],
            "type": "pubkey"
          },
          {
            "name": "app_account",
            "docs": [
              "App-owned account whose encrypted field this lineage represents."
            ],
            "type": "pubkey"
          },
          {
            "name": "encrypted_value_label",
            "docs": [
              "Domain-separated encrypted field label inside `app_account`."
            ],
            "type": {
              "array": [
                "u8",
                32
              ]
            }
          },
          {
            "name": "current_handle",
            "docs": [
              "Current encrypted value identifier (the live handle)."
            ],
            "type": {
              "array": [
                "u8",
                32
              ]
            }
          },
          {
            "name": "subjects",
            "docs": [
              "Current durable subjects. Membership in this set is the whole ACL."
            ],
            "type": {
              "vec": "pubkey"
            }
          },
          {
            "name": "leaf_count",
            "docs": [
              "Number of MMR leaves appended; `0` means no history."
            ],
            "type": "u64"
          },
          {
            "name": "peaks",
            "docs": [
              "MMR peaks, oldest mountain first (`popcount(leaf_count)` entries)."
            ],
            "type": {
              "vec": {
                "array": [
                  "u8",
                  32
                ]
              }
            }
          },
          {
            "name": "bump",
            "docs": [
              "PDA bump."
            ],
            "type": "u8"
          }
        ]
      }
    },
    {
      "name": "HandleDisclosedEvent",
      "docs": [
        "Emitted when `disclose_secp` publishes a KMS-certified cleartext for a token-scoped handle.",
        "",
        "This is the single app-level disclosure event after the `DisclosureRequest` lifecycle was",
        "dissolved (fhevm-internal#1704): it covers both former balance and amount disclosures. It carries",
        "no request witness or `request_hash` — there is no per-request PDA anymore. The request side is",
        "the owner sealing a public-decrypt leaf via the host `make_handle_public` instruction directly."
      ],
      "type": {
        "kind": "struct",
        "fields": [
          {
            "name": "version",
            "docs": [
              "Event schema version."
            ],
            "type": "u8"
          },
          {
            "name": "mint",
            "docs": [
              "Confidential mint whose ACL domain scopes the disclosed lineage."
            ],
            "type": "pubkey"
          },
          {
            "name": "handle",
            "docs": [
              "Disclosed handle, proven public by the host verifier."
            ],
            "type": {
              "array": [
                "u8",
                32
              ]
            }
          },
          {
            "name": "encrypted_value",
            "docs": [
              "ZamaHost `EncryptedValue` lineage the handle belongs to."
            ],
            "type": "pubkey"
          },
          {
            "name": "cleartext_amount",
            "docs": [
              "KMS-certified cleartext amount (low 64 bits of the certified `uint256`)."
            ],
            "type": "u64"
          }
        ]
      }
    },
    {
      "name": "HostConfig",
      "docs": [
        "Singleton host configuration and authority surface.",
        "",
        "`HostConfig` is the runtime switchboard for this PoC. Production-shaped",
        "instructions reject while paused."
      ],
      "type": {
        "kind": "struct",
        "fields": [
          {
            "name": "admin",
            "docs": [
              "Program administrator allowed to update config flags."
            ],
            "type": "pubkey"
          },
          {
            "name": "chain_id",
            "docs": [
              "Host-chain id included in handle derivation."
            ],
            "type": "u64"
          },
          {
            "name": "gateway_chain_id",
            "docs": [
              "EVM gateway chain id used in the coprocessor/KMS EIP-712 domain separators."
            ],
            "type": "u64"
          },
          {
            "name": "input_verification_contract",
            "docs": [
              "EVM `InputVerification` contract address: the EIP-712 verifying contract for",
              "coprocessor `CiphertextVerification` input attestations."
            ],
            "type": {
              "array": [
                "u8",
                20
              ]
            }
          },
          {
            "name": "coprocessor_signers",
            "docs": [
              "Registered coprocessor EVM signer set for input attestations (EVM `InputVerifier`",
              "parity). Fixed-capacity so `HostConfig` keeps a pinned byte layout; only the first",
              "`coprocessor_signer_count` entries are active, the rest are zero padding."
            ],
            "type": {
              "array": [
                {
                  "array": [
                    "u8",
                    20
                  ]
                },
                8
              ]
            }
          },
          {
            "name": "coprocessor_signer_count",
            "docs": [
              "Number of active entries in `coprocessor_signers`."
            ],
            "type": "u8"
          },
          {
            "name": "coprocessor_threshold",
            "docs": [
              "Minimum distinct valid signatures (n-of-m) required over an input attestation;",
              "`1 <= coprocessor_threshold <= coprocessor_signer_count`."
            ],
            "type": "u8"
          },
          {
            "name": "decryption_contract",
            "docs": [
              "EVM `Decryption` contract address: the EIP-712 verifying contract for KMS",
              "`PublicDecryptVerification` certificates (disclose/redeem)."
            ],
            "type": {
              "array": [
                "u8",
                20
              ]
            }
          },
          {
            "name": "current_kms_context_id",
            "docs": [
              "Active KMS context id (mirrors `ProtocolConfig.getCurrentKmsContextId`). The",
              "signer set + thresholds live in the `KmsContext` PDA at this id; 0 means none",
              "defined yet. Updated by `define_kms_context`."
            ],
            "type": "u64"
          },
          {
            "name": "paused",
            "docs": [
              "Pauses production-shaped host instructions when true."
            ],
            "type": "bool"
          },
          {
            "name": "grant_deny_list_enabled",
            "docs": [
              "Enables deny-list checks for persistent grant authorities."
            ],
            "type": "bool"
          },
          {
            "name": "max_hcu_per_tx",
            "docs": [
              "Max total HCU summed over one `fhe_eval` plan. `0` = unlimited (enforcement off)."
            ],
            "type": "u64"
          },
          {
            "name": "max_hcu_depth_per_tx",
            "docs": [
              "Max critical-path (depth) HCU within one `fhe_eval` plan. `0` = unlimited."
            ],
            "type": "u64"
          },
          {
            "name": "hcu_block_cap_per_app",
            "docs": [
              "Per-app HCU budget per slot, enforced in `fhe_eval`. `u64::MAX` = unrestricted (the ship",
              "default; short-circuits, touching no meter); `0` = ban untrusted apps (trusted still bypass);",
              "any other value is the metering band (must be `>= max_hcu_per_tx` unless that is `0`)."
            ],
            "type": "u64"
          },
          {
            "name": "updated_slot",
            "docs": [
              "Slot in which the config was initialized or last changed."
            ],
            "type": "u64"
          },
          {
            "name": "bump",
            "docs": [
              "PDA bump for `PDA(\"host-config\")`."
            ],
            "type": "u8"
          }
        ]
      }
    },
    {
      "name": "KmsContext",
      "docs": [
        "A KMS context: the signer set + thresholds active under a `context_id`."
      ],
      "type": {
        "kind": "struct",
        "fields": [
          {
            "name": "context_id",
            "docs": [
              "Monotonic context id (mirrors `kmsContextId`)."
            ],
            "type": "u64"
          },
          {
            "name": "signers",
            "docs": [
              "KMS node signer EVM addresses authorized to sign certs in this context."
            ],
            "type": {
              "vec": {
                "array": [
                  "u8",
                  20
                ]
              }
            }
          },
          {
            "name": "thresholds",
            "docs": [
              "Per-operation signature thresholds."
            ],
            "type": {
              "defined": {
                "name": "KmsThresholds"
              }
            }
          },
          {
            "name": "destroyed",
            "docs": [
              "True once destroyed (mirrors `destroyKmsContext`); destroyed contexts reject."
            ],
            "type": "bool"
          },
          {
            "name": "bump",
            "docs": [
              "PDA bump for `PDA(\"kms-context\", context_id)`."
            ],
            "type": "u8"
          }
        ]
      }
    },
    {
      "name": "KmsThresholds",
      "docs": [
        "Per-operation signature thresholds for a KMS context (mirrors `KmsThresholds`)."
      ],
      "type": {
        "kind": "struct",
        "fields": [
          {
            "name": "public_decryption",
            "docs": [
              "Threshold for public-decrypt (disclose/redeem) certificates."
            ],
            "type": "u8"
          },
          {
            "name": "user_decryption",
            "docs": [
              "Threshold for user-decrypt certificates."
            ],
            "type": "u8"
          },
          {
            "name": "kms_gen",
            "docs": [
              "Threshold for key generation (KMS-internal; stored for fidelity)."
            ],
            "type": "u8"
          },
          {
            "name": "mpc",
            "docs": [
              "Threshold for MPC (KMS-internal; stored for fidelity)."
            ],
            "type": "u8"
          }
        ]
      }
    },
    {
      "name": "MmrInclusionProof",
      "docs": [
        "Anchor-native mirror of `zama_solana_acl::MmrProof` for use as an instruction argument. The",
        "shared ACL crate is deliberately Anchor-free (pure `borsh`) so it cannot derive Anchor IDL",
        "metadata; this local type carries the identical wire shape and converts into the shared proof.",
        "Defined in the host program so CPI callers depend only on the host IDL, never on token types."
      ],
      "type": {
        "kind": "struct",
        "fields": [
          {
            "name": "leaf_index",
            "docs": [
              "Index of the proven leaf within the lineage's MMR."
            ],
            "type": "u64"
          },
          {
            "name": "siblings",
            "docs": [
              "Authentication path from the leaf up to its mountain peak."
            ],
            "type": {
              "vec": {
                "array": [
                  "u8",
                  32
                ]
              }
            }
          }
        ]
      }
    },
    {
      "name": "RandomAmountCreatedEvent",
      "docs": [
        "Emitted when the token program creates a token-scoped random amount."
      ],
      "type": {
        "kind": "struct",
        "fields": [
          {
            "name": "version",
            "docs": [
              "Event schema version."
            ],
            "type": "u8"
          },
          {
            "name": "mint",
            "docs": [
              "Confidential mint."
            ],
            "type": "pubkey"
          },
          {
            "name": "owner",
            "docs": [
              "Token account owner."
            ],
            "type": "pubkey"
          },
          {
            "name": "token_account",
            "docs": [
              "Confidential token account."
            ],
            "type": "pubkey"
          },
          {
            "name": "amount_kind",
            "docs": [
              "Whether this amount is intended for transfer or burn."
            ],
            "type": {
              "defined": {
                "name": "ConfidentialAmountKind"
              }
            }
          },
          {
            "name": "handle",
            "docs": [
              "Newly created amount handle."
            ],
            "type": {
              "array": [
                "u8",
                32
              ]
            }
          },
          {
            "name": "encrypted_value",
            "docs": [
              "ZamaHost ACL record initialized for the amount."
            ],
            "type": "pubkey"
          }
        ]
      }
    },
    {
      "name": "TotalSupplyHandleUpdatedEvent",
      "docs": [
        "App-local total-supply history event.",
        "",
        "This mirrors ERC7984's encrypted `_totalSupply` pointer at the Solana mint",
        "level. The generic coprocessor listener consumes ZamaHost protocol events;",
        "this event is for token-aware indexers."
      ],
      "type": {
        "kind": "struct",
        "fields": [
          {
            "name": "version",
            "docs": [
              "Event schema version."
            ],
            "type": "u8"
          },
          {
            "name": "mint",
            "docs": [
              "Confidential mint."
            ],
            "type": "pubkey"
          },
          {
            "name": "old_handle",
            "docs": [
              "Previous total-supply handle."
            ],
            "type": {
              "array": [
                "u8",
                32
              ]
            }
          },
          {
            "name": "old_encrypted_value",
            "docs": [
              "Previous ZamaHost ACL record."
            ],
            "type": "pubkey"
          },
          {
            "name": "new_handle",
            "docs": [
              "New total-supply handle."
            ],
            "type": {
              "array": [
                "u8",
                32
              ]
            }
          },
          {
            "name": "new_encrypted_value",
            "docs": [
              "New ZamaHost ACL record."
            ],
            "type": "pubkey"
          },
          {
            "name": "reason",
            "docs": [
              "Reason this total-supply pointer changed."
            ],
            "type": {
              "defined": {
                "name": "TotalSupplyUpdateReason"
              }
            }
          }
        ]
      }
    },
    {
      "name": "TotalSupplyUpdateReason",
      "docs": [
        "Reason code for [`TotalSupplyHandleUpdatedEvent`]."
      ],
      "type": {
        "kind": "enum",
        "variants": [
          {
            "name": "Initialize"
          },
          {
            "name": "Wrap"
          },
          {
            "name": "Burn"
          }
        ]
      }
    }
  ]
}